google_images_download/__init__.py
google_images_download/__main__.py
google_images_download/google_images_download.py
google_images_download_joe-2.8.0.dist-info/METADATA
google_images_download_joe-2.8.0.dist-info/WHEEL
google_images_download_joe-2.8.0.dist-info/entry_points.txt
google_images_download_joe-2.8.0.dist-info/top_level.txt
google_images_download_joe-2.8.0.dist-info/RECORD
