Metadata-Version: 2.1
Name: google-images-download-joe
Version: 2.8.0
Summary: Python Script to download hundreds of images from 'Google Images'. It is a ready-to-run code! 
Home-page: https://github.com/hardikvasa/google-images-download
Author: Hardik Vasa
Author-email: hnvasa@gmail.com
License: MIT
Download-URL: https://github.com/hardikvasa/google-images-download/tarball/2.8.0
Keywords: google images download save filter color image-search image-dataset image-scrapper image-gallery terminal command-line
Platform: UNKNOWN
Classifier: Development Status :: 4 - Beta
Classifier: Intended Audience :: Developers
Classifier: License :: OSI Approved :: MIT License
Classifier: Programming Language :: Python :: 2.7
Classifier: Programming Language :: Python :: 3.3
Classifier: Programming Language :: Python :: 3.4
Classifier: Programming Language :: Python :: 3.5
Classifier: Programming Language :: Python :: 3.6
Requires-Dist: selenium
